summa_pkg/__init__.py
summa_pkg/summa.py
summa_pkg-0.1.0.dist-info/WHEEL
summa_pkg-0.1.0.dist-info/METADATA
summa_pkg-0.1.0.dist-info/RECORD
