Metadata-Version: 2.1
Name: summa-pkg
Version: 0.1.0
Summary: 
Author: romansnetkov
Author-email: snetkov.roman@gmail.com
Requires-Python: >=3.7,<4.0
Classifier: Programming Language :: Python :: 3
Classifier: Programming Language :: Python :: 3.7
Classifier: Programming Language :: Python :: 3.8
Classifier: Programming Language :: Python :: 3.9
Requires-Dist: torch (>=1.9.0,<2.0.0)
